{
  "db_name": "SQLite",
  "query": "INSERT INTO deployments(id, name, description) VALUES (?, ?, ?) RETURNING *",
  "describe": {
    "columns": [
      {
        "name": "id",
        "ordinal": 0,
        "type_info": "Text"
      },
      {
        "name": "name",
        "ordinal": 1,
        "type_info": "Text"
      },
      {
        "name": "description",
        "ordinal": 2,
        "type_info": "Text"
      },
      {
        "name": "created_at",
        "ordinal": 3,
        "type_info": "Datetime"
      }
    ],
    "parameters": {
      "Right": 3
    },
    "nullable": [
      false,
      false,
      false,
      false
    ]
  },
  "hash": "951ad482a5be6d4aefb8e511f75354a14b09ed413c7f92e7ca0f594fe78fc8e5"
}
